HybridAndroidDriver/__init__.py
HybridAndroidDriver/asset/app-debug-androidTest.apk
HybridAndroidDriver/asset/app-debug.apk
HybridAndroidDriver/asset/chromedriver.exe
HybridAndroidDriver-0.3.dist-info/DESCRIPTION.rst
HybridAndroidDriver-0.3.dist-info/METADATA
HybridAndroidDriver-0.3.dist-info/RECORD
HybridAndroidDriver-0.3.dist-info/WHEEL
HybridAndroidDriver-0.3.dist-info/metadata.json
HybridAndroidDriver-0.3.dist-info/top_level.txt
