Metadata-Version: 2.0
Name: HybridAndroidDriver
Version: 0.3
Summary: android driver for native and webview or hybrid
Home-page: http://github.com/sssvip/HybridAndroidDriver
Author: sssvip
Author-email: admin@dxscx.com
License: MIT
Keywords: android hybrid driver
Platform: any
Requires-Dist: requests
